alchemical_storage/__init__.py
alchemical_storage/filter/__init__.py
alchemical_storage/filter/exc.py
alchemical_storage/filter/filter.py
alchemical_storage/index/__init__.py
alchemical_storage/index/index.py
alchemical_storage/join.py
alchemical_storage/py.typed
alchemical_storage/storage/__init__.py
alchemical_storage/storage/exc.py
alchemical_storage/storage/storage.py
alchemical_storage/visitor.py
alchemical_storage-1.0.1.dist-info/LICENSE
alchemical_storage-1.0.1.dist-info/METADATA
alchemical_storage-1.0.1.dist-info/WHEEL
alchemical_storage-1.0.1.dist-info/RECORD
