Metadata-Version: 2.1
Name: alchemical-storage
Version: 1.0.1
Summary: Storage based off of sqlalchemy_marshmallow
License: MIT
Author: Cory Laughlin
Author-email: corylcomposinger@gmail.com
Requires-Python: >=3.10,<3.13
Classifier: License :: OSI Approved :: MIT License
Classifier: Programming Language :: Python :: 3
Classifier: Programming Language :: Python :: 3.10
Classifier: Programming Language :: Python :: 3.11
Classifier: Programming Language :: Python :: 3.12
Requires-Dist: marshmallow-sqlalchemy (>=0.28.0,<2.0)
Requires-Dist: sqlalchemy (>=2.0.19,<3.0.0)
